{
  "item.slashblade.proudsoul_tiny": "骄傲的小灵魂",
  "adv.slashblade.proudsoul_trapezohedron": "无限炼化\n冒烟\n到达终点的刀魂。",
  "adv.slashblade.storm_swords": "射击艺术-风暴剑-",
  "item.slashblade.simple.bamboo.desc": "未完成的仿刀片",
  "item.slashblade.ex.fox.white.material": "刀片组件-WhiteFox-",
  "adv.slashblade.white_broken": "断边",
  "adv.slashblade.rising_star": "剑术-新星-",
  "adv.slashblade.proudsoul": "精炼上限\u003d50\n刀刃易碎。\n灵魂永不浪费。",
  "item.slashblade.proudsoul_tiny.dark": "摇篮之刃灵魂",
  "item.slashblade.ex.ruby.material": "刀片组件-Ruby-",
  "item.slashblade.proudsoul": "骄傲的灵魂",
  "item.slashblade.simple.bamboo": "匿名-竹灯-",
  "slashblade.tooltip.material.enchantments": "结界",
  "item.slashblade.ex.fox.white.desc": "幸运征兆",
  "item.slashblade.ex.tukumo.material": "叶片组件-Tukumo-",
  "item.slashblade.ex.muramasa.desc": "失落的村正剑之一。",
  "adv.slashblade.white_broken.desc": "重铸！",
  "adv.slashblade.movesets.desc": "控制",
  "adv.slashblade.exeffect.desc": "额外附魔效果",
  "slashblade.tooltip.refine": "精炼：%1$s",
  "attribute.name.generic.reachDistance": "抵达",
  "item.slashblade.simple.silverbamboo": "注明-银竹灯-",
  "adv.slashblade.imitation_broken": "这是假的。",
  "adv.slashblade.spiral_swords": "射击艺术-螺旋剑-",
  "adv.slashblade.proudsoul_tiny": "精炼上限\u003d10\n神秘的燃烧灵魂。",
  "slashblade.tooltip.material.noscabbard": "无刀鞘",
  "adv.slashblade.aerial_cleave": "剑术-空中劈砍-",
  "itemGroup.slashblade": "斩刃",
  "adv.slashblade.exeffect": "前结界效果",
  "adv.slashblade.reforge": "重铸之刃",
  "item.slashblade.simple.silverbamboo.desc": "仿品",
  "adv.slashblade.exeffect.soul_speed.desc": "每升一级魂速，单纯动作的输入时间限制就会延长1个刻度。",
  "slashblade.tooltip.material.killcount": "%1$s \u003c\u003d 杀戮计数",
  "adv.slashblade.judgement_cut": "剑术-审判斩-",
  "adv.slashblade.refine": "刀片精炼",
  "item.slashblade.simple.iron": "斩刃——",
  "item.slashblade.ex.muramasa.material": "刀片组件-Muramasa-",
  "slashblade.tooltip.material.broken": "破碎的",
  "adv.slashblade.proudsoul_ingot": "精炼上限\u003d100\n用燃烧的灵魂锻造的钢铁。",
  "item.slashblade.simple.iron.material": "刀片组件-铁-",
  "adv.slashblade.combo_a_ex": "Blade Arts -Combo A EX-",
  "adv.slashblade.guard": "能力-守卫-",
  "adv.slashblade.proudsoul_awakened": "被唤醒",
  "adv.slashblade.enemy_step": "能力-敌步-",
  "item.slashblade.ex.fox.white": "-Weiss- 樱花狐",
  "item.slashblade.simple.silverbamboo.material": "刀片组件-仿-",
  "item.slashblade.proudsoul_ingot": "刀魂锭",
  "adv.slashblade.bladestand": "刀片架",
  "adv.slashblade.air_trick": "能力-空中技巧-",
  "item.slashblade.slashblade.desc": "同类相食维护\n纯粹的容器。",
  "item.slashblade.simple.iron.desc": "基本刀片",
  "adv.slashblade.movesets": "刀片移动组",
  "item.slashblade.ex.fox.black.material": "刀片组件-BlackFox-",
  "stat.slashblade.sword_summoned": "召唤剑",
  "item.slashblade.proudsoul_sphere": "刀魂球",
  "adv.slashblade.trick_up": "能力-Trick Up-",
  "adv.slashblade.guard_just": "能力-守护-",
  "item.slashblade.simple.white.material": "刀片组件-白色-",
  "item.slashblade.simple.wood": "匿名-木-",
  "adv.slashblade.heavy_rain_swords": "射击艺术-大雨剑-",
  "adv.slashblade.aerial_a": "Blade Arts -Aerial Rave A-",
  "adv.slashblade.aerial_b": "Blade Arts -空中狂欢 B-",
  "adv.slashblade.reforge.desc": "刀片和部件使用砧座组装。",
  "itemGroup.slashblade.desc": "堕入阿修罗界。",
  "item.slashblade.simple.wood.desc": "有鞘的木剑。",
  "adv.slashblade.judgement_cut_just": "刀剑艺术 -Judgement Cut EX-",
  "adv.slashblade.exeffect.feather_falling.desc": "空中行动时的坠落速度会根据羽毛掉落等级而降低。",
  "item.slashblade.simple.bamboo.material": "刀片组件-竹-",
  "adv.slashblade.proudsoul_activated": "饥饿\n潜行并使用",
  "item.slashblade.bladestand_v": "刀片架垂直",
  "adv.slashblade.combo_b_max": "Combo B 最大延伸",
  "item.slashblade.proudsoul_crystal": "刀魂水晶",
  "item.slashblade.bladestand_s": "短刀片架",
  "adv.slashblade.exeffect.soul_speed": "轻松行动",
  "adv.slashblade.bladestand.desc": "休息刀片的地方。",
  "item.slashblade.slashblade": "匿名-无名-",
  "adv.slashblade.exeffect.feather_falling": "缓慢下降",
  "item.slashblade.simple.white": "清晰度-白色-",
  "adv.slashblade.quick_charge": "Blade Arts -快速充电-",
  "adv.slashblade.rapid_slash": "剑术-急斩-",
  "item.slashblade.proudsoul_awakened": "觉醒的刀魂",
  "item.slashblade.ex.ruby.desc": "高级一号",
  "adv.slashblade.proudsoul_crystal": "精炼上限\u003d200\n爆破\n刀魂核心。",
  "item.slashblade.bladestand_2w": "Blade 墙架双",
  "item.slashblade.ex.ruby": "锋利度-无名-红宝石",
  "item.slashblade.ex.fox.black": "-雾霾- 樱花狐",
  "adv.slashblade.combo_b": "剑术 -Combo B-",
  "adv.slashblade.combo_a": "剑术 -Combo A-",
  "adv.slashblade.blistering_swords": "射击艺术-起泡剑-",
  "adv.slashblade.combo_c": "剑术-Combo C-",
  "adv.slashblade.combo_b_max.desc": "撕碎！",
  "item.slashblade.bladestand_1": "单刀片架",
  "item.slashblade.bladestand_2": "双刀片架",
  "item.slashblade.ex.tukumo.desc": "铁木剑文章",
  "slashblade.tooltip.material": "所需工艺条件",
  "adv.slashblade.upperslash": "剑术-上斜线-",
  "item.slashblade.bladestand_1w": "单刀片墙架",
  "item.slashblade.proudsoul_activated": "激活刀魂",
  "adv.slashblade.refine.desc": "每次精炼时，刀片的潜力都会增加。",
  "item.slashblade.ex.muramasa": "-千鹤- 村正",
  "item.slashblade.proudsoul_trapezohedron": "刀魂偏方体",
  "slashblade.tooltip.material.requiredobjects.anvil": "所需物品：铁砧",
  "adv.slashblade.summonedswords": "射击术-召唤剑-",
  "item.slashblade.ex.tukumo": "高贵-Tukumo-紫罗兰",
  "slashblade.tooltip.material.level": "%1$s \u003c\u003d 玩家等级",
  "adv.slashblade.upperslash_jump": "剑术-跳跃斩-",
  "adv.slashblade.trick_dodge": "能力-诡计闪避-",
  "adv.slashblade.proudsoul_sphere": "精炼上限\u003d150\n熔炼\n带有微弱火焰的钢之宝石。",
  "adv.slashblade.kick_jump": "能力-踢跳-",
  "slashblade.tooltip.material.refine": "%1$s \u003c\u003d 精炼",
  "item.slashblade.simple.white.desc": "铁刃",
  "adv.slashblade.trick_down": "能力-Trick Down-"
}